LICENSE
MANIFEST.in
README.rst
setup.py
scripts/loose_ssh.sh
scripts/stackstrap
stackstrap/__init__.py
stackstrap/cli.py
stackstrap/config.py
stackstrap/jinja.py
stackstrap/project.py
stackstrap/repository.py
stackstrap/template.py
stackstrap.egg-info/PKG-INFO
stackstrap.egg-info/SOURCES.txt
stackstrap.egg-info/dependency_links.txt
stackstrap.egg-info/requires.txt
stackstrap.egg-info/top_level.txt
stackstrap/commands/__init__.py
stackstrap/commands/__init__.pyc
stackstrap/commands/create.py
stackstrap/commands/create.pyc
stackstrap/commands/template/__init__.py
stackstrap/commands/template/__init__.pyc
stackstrap/commands/template/add.py
stackstrap/commands/template/add.pyc
stackstrap/commands/template/create.py
stackstrap/commands/template/create.pyc
stackstrap/commands/template/list.py
stackstrap/commands/template/list.pyc
stackstrap/commands/template/remove.py
stackstrap/commands/template/remove.pyc