Metadata-Version: 1.1
Name: stackstrap
Version: 0.2.2
Summary: A tool that uses vagrant + salt to make development more awesome
Home-page: https://github.com/freesurface/stackstrap
Author: Evan Borgstrom
Author-email: evan@borgstrom.ca
License: Apache License, Version 2.0
Platform: UNKNOWN
Classifier: Development Status :: 4 - Beta
Classifier: Intended Audience :: Developers
Classifier: License :: OSI Approved :: Apache Software License
Classifier: Natural Language :: English
Classifier: Topic :: Software Development :: Libraries
Classifier: Topic :: Software Development :: Libraries :: Python Modules
